health_indicator/__init__.py
health_indicator/health_indicator.py
health_indicator-0.0.4.dist-info/METADATA
health_indicator-0.0.4.dist-info/WHEEL
health_indicator-0.0.4.dist-info/RECORD
