Metadata-Version: 2.1
Name: health-indicator
Version: 0.0.4
Summary: 
License: MIT
Author: Xiangyi Yin
Author-email: xiangyi.yin@capco.com
Requires-Python: >=3.9,<4.0
Classifier: License :: OSI Approved :: MIT License
Classifier: Programming Language :: Python :: 3
Classifier: Programming Language :: Python :: 3.9
Classifier: Programming Language :: Python :: 3.10
Classifier: Programming Language :: Python :: 3.11
